flask_make/__init__.py
flask_make-1.0.6.dist-info/METADATA
flask_make-1.0.6.dist-info/WHEEL
flask_make-1.0.6.dist-info/entry_points.txt
flask_make-1.0.6.dist-info/licenses/LICENSE
flask_make-1.0.6.dist-info/RECORD
