Metadata-Version: 2.3
Name: flask_make
Version: 1.0.6
Summary: A custom CLI command to create a new Flask app with a basic structure, creates virtual environment and installs requirements
Project-URL: Homepage, https://github.com/dilrajs616/flask-make
Project-URL: Issues, https://github.com/dilrajs616/flask-make/discussions
Author-email: Dilraj Singh <dilraj082@gmail.com>
License: MIT
Keywords: app,flask,template
Classifier: Framework :: Flask
Classifier: License :: OSI Approved :: MIT License
Classifier: Programming Language :: Python :: 3
Requires-Python: >=3.8
